{"GRID_TYPE":{"0":"Shot Chart Detail","1":"Shot Chart Detail","2":"Shot Chart Detail","3":"Shot Chart Detail","4":"Shot Chart Detail","5":"Shot Chart Detail","6":"Shot Chart Detail","7":"Shot Chart Detail","8":"Shot Chart Detail","9":"Shot Chart Detail","10":"Shot Chart Detail","11":"Shot Chart Detail","12":"Shot Chart Detail","13":"Shot Chart Detail","14":"Shot Chart Detail","15":"Shot Chart Detail","16":"Shot Chart Detail","17":"Shot Chart Detail","18":"Shot Chart Detail"},"GAME_ID":{"0":"0022000015","1":"0022000015","2":"0022000015","3":"0022000015","4":"0022000015","5":"0022000015","6":"0022000026","7":"0022000073","8":"0022000073","9":"0022000073","10":"0022000073","11":"0022000131","12":"0022000131","13":"0022000131","14":"0022000656","15":"0022000881","16":"0022000881","17":"0022000937","18":"0022001060"},"GAME_EVENT_ID":{"0":165,"1":412,"2":416,"3":590,"4":600,"5":700,"6":668,"7":573,"8":580,"9":593,"10":626,"11":414,"12":419,"13":472,"14":627,"15":649,"16":653,"17":607,"18":646},"PLAYER_ID":{"0":1629690,"1":1629690,"2":1629690,"3":1629690,"4":1629690,"5":1629690,"6":1629690,"7":1629690,"8":1629690,"9":1629690,"10":1629690,"11":1629690,"12":1629690,"13":1629690,"14":1629690,"15":1629690,"16":1629690,"17":1629690,"18":1629690},"PLAYER_NAME":{"0":"Adam Mokoka","1":"Adam Mokoka","2":"Adam Mokoka","3":"Adam Mokoka","4":"Adam Mokoka","5":"Adam Mokoka","6":"Adam Mokoka","7":"Adam Mokoka","8":"Adam Mokoka","9":"Adam Mokoka","10":"Adam Mokoka","11":"Adam Mokoka","12":"Adam Mokoka","13":"Adam Mokoka","14":"Adam Mokoka","15":"Adam Mokoka","16":"Adam Mokoka","17":"Adam Mokoka","18":"Adam Mokoka"},"TEAM_ID":{"0":1610612741,"1":1610612741,"2":1610612741,"3":1610612741,"4":1610612741,"5":1610612741,"6":1610612741,"7":1610612741,"8":1610612741,"9":1610612741,"10":1610612741,"11":1610612741,"12":1610612741,"13":1610612741,"14":1610612741,"15":1610612741,"16":1610612741,"17":1610612741,"18":1610612741},"TEAM_NAME":{"0":"Chicago Bulls","1":"Chicago Bulls","2":"Chicago Bulls","3":"Chicago Bulls","4":"Chicago Bulls","5":"Chicago Bulls","6":"Chicago Bulls","7":"Chicago Bulls","8":"Chicago Bulls","9":"Chicago Bulls","10":"Chicago Bulls","11":"Chicago Bulls","12":"Chicago Bulls","13":"Chicago Bulls","14":"Chicago Bulls","15":"Chicago Bulls","16":"Chicago Bulls","17":"Chicago Bulls","18":"Chicago Bulls"},"PERIOD":{"0":1,"1":3,"2":3,"3":4,"4":4,"5":4,"6":4,"7":4,"8":4,"9":4,"10":4,"11":3,"12":3,"13":4,"14":4,"15":4,"16":4,"17":4,"18":4},"MINUTES_REMAINING":{"0":0,"1":9,"2":8,"3":8,"4":8,"5":0,"6":2,"7":8,"8":7,"9":6,"10":4,"11":3,"12":2,"13":10,"14":0,"15":1,"16":0,"17":0,"18":0},"SECONDS_REMAINING":{"0":27,"1":18,"2":41,"3":42,"4":8,"5":57,"6":30,"7":24,"8":29,"9":57,"10":58,"11":19,"12":51,"13":59,"14":59,"15":3,"16":37,"17":20,"18":37},"EVENT_TYPE":{"0":"Missed Shot","1":"Missed Shot","2":"Missed Shot","3":"Made Shot","4":"Made Shot","5":"Missed Shot","6":"Missed Shot","7":"Missed Shot","8":"Made Shot","9":"Missed Shot","10":"Made Shot","11":"Made Shot","12":"Missed Shot","13":"Missed Shot","14":"Made Shot","15":"Missed Shot","16":"Made Shot","17":"Missed Shot","18":"Missed Shot"},"ACTION_TYPE":{"0":"Jump Shot","1":"Driving Reverse Layup Shot","2":"Jump Shot","3":"Driving Layup Shot","4":"Putback Layup Shot","5":"Jump Shot","6":"Step Back Jump shot","7":"Jump Shot","8":"Running Layup Shot","9":"Jump Shot","10":"Running Layup Shot","11":"Jump Shot","12":"Jump Shot","13":"Layup Shot","14":"Running Layup Shot","15":"Jump Shot","16":"Cutting Layup Shot","17":"Step Back Jump shot","18":"Driving Layup Shot"},"SHOT_TYPE":{"0":"3PT Field Goal","1":"2PT Field Goal","2":"3PT Field Goal","3":"2PT Field Goal","4":"2PT Field Goal","5":"3PT Field Goal","6":"3PT Field Goal","7":"3PT Field Goal","8":"2PT Field Goal","9":"3PT Field Goal","10":"2PT Field Goal","11":"3PT Field Goal","12":"3PT Field Goal","13":"2PT Field Goal","14":"2PT Field Goal","15":"3PT Field Goal","16":"2PT Field Goal","17":"3PT Field Goal","18":"2PT Field Goal"},"SHOT_ZONE_BASIC":{"0":"Right Corner 3","1":"Restricted Area","2":"Above the Break 3","3":"Restricted Area","4":"Restricted Area","5":"Above the Break 3","6":"Right Corner 3","7":"Above the Break 3","8":"Restricted Area","9":"Right Corner 3","10":"Restricted Area","11":"Left Corner 3","12":"Left Corner 3","13":"Restricted Area","14":"Restricted Area","15":"Above the Break 3","16":"Restricted Area","17":"Above the Break 3","18":"Restricted Area"},"SHOT_ZONE_AREA":{"0":"Right Side(R)","1":"Center(C)","2":"Left Side Center(LC)","3":"Center(C)","4":"Center(C)","5":"Center(C)","6":"Right Side(R)","7":"Center(C)","8":"Center(C)","9":"Right Side(R)","10":"Center(C)","11":"Left Side(L)","12":"Left Side(L)","13":"Center(C)","14":"Center(C)","15":"Left Side Center(LC)","16":"Center(C)","17":"Right Side Center(RC)","18":"Center(C)"},"SHOT_ZONE_RANGE":{"0":"24+ ft.","1":"Less Than 8 ft.","2":"24+ ft.","3":"Less Than 8 ft.","4":"Less Than 8 ft.","5":"24+ ft.","6":"24+ ft.","7":"24+ ft.","8":"Less Than 8 ft.","9":"24+ ft.","10":"Less Than 8 ft.","11":"24+ ft.","12":"24+ ft.","13":"Less Than 8 ft.","14":"Less Than 8 ft.","15":"24+ ft.","16":"Less Than 8 ft.","17":"24+ ft.","18":"Less Than 8 ft."},"SHOT_DISTANCE":{"0":22,"1":1,"2":24,"3":1,"4":0,"5":25,"6":22,"7":27,"8":1,"9":24,"10":2,"11":23,"12":22,"13":3,"14":2,"15":26,"16":1,"17":24,"18":1},"LOC_X":{"0":221,"1":-13,"2":-210,"3":11,"4":-3,"5":-62,"6":220,"7":68,"8":5,"9":231,"10":3,"11":-233,"12":-228,"13":-30,"14":-21,"15":-140,"16":8,"17":212,"18":12},"LOC_Y":{"0":48,"1":1,"2":126,"3":0,"4":4,"5":251,"6":48,"7":265,"8":16,"9":75,"10":22,"11":22,"12":20,"13":14,"14":8,"15":221,"16":15,"17":132,"18":13},"SHOT_ATTEMPTED_FLAG":{"0":1,"1":1,"2":1,"3":1,"4":1,"5":1,"6":1,"7":1,"8":1,"9":1,"10":1,"11":1,"12":1,"13":1,"14":1,"15":1,"16":1,"17":1,"18":1},"SHOT_MADE_FLAG":{"0":0,"1":0,"2":0,"3":1,"4":1,"5":0,"6":0,"7":0,"8":1,"9":0,"10":1,"11":1,"12":0,"13":0,"14":1,"15":0,"16":1,"17":0,"18":0},"GAME_DATE":{"0":"20201223","1":"20201223","2":"20201223","3":"20201223","4":"20201223","5":"20201223","6":"20201226","7":"20210101","8":"20210101","9":"20210101","10":"20210101","11":"20210108","12":"20210108","13":"20210108","14":"20210322","15":"20210421","16":"20210421","17":"20210428","18":"20210515"},"HTM":{"0":"CHI","1":"CHI","2":"CHI","3":"CHI","4":"CHI","5":"CHI","6":"CHI","7":"MIL","8":"MIL","9":"MIL","10":"MIL","11":"LAL","12":"LAL","13":"LAL","14":"CHI","15":"CLE","16":"CLE","17":"NYK","18":"BKN"},"VTM":{"0":"ATL","1":"ATL","2":"ATL","3":"ATL","4":"ATL","5":"ATL","6":"IND","7":"CHI","8":"CHI","9":"CHI","10":"CHI","11":"CHI","12":"CHI","13":"CHI","14":"UTA","15":"CHI","16":"CHI","17":"CHI","18":"CHI"}}