{"GRID_TYPE":{"0":"Shot Chart Detail","1":"Shot Chart Detail","2":"Shot Chart Detail","3":"Shot Chart Detail","4":"Shot Chart Detail","5":"Shot Chart Detail","6":"Shot Chart Detail","7":"Shot Chart Detail","8":"Shot Chart Detail","9":"Shot Chart Detail","10":"Shot Chart Detail","11":"Shot Chart Detail","12":"Shot Chart Detail","13":"Shot Chart Detail","14":"Shot Chart Detail","15":"Shot Chart Detail","16":"Shot Chart Detail","17":"Shot Chart Detail","18":"Shot Chart Detail","19":"Shot Chart Detail","20":"Shot Chart Detail","21":"Shot Chart Detail","22":"Shot Chart Detail","23":"Shot Chart Detail","24":"Shot Chart Detail","25":"Shot Chart Detail","26":"Shot Chart Detail"},"GAME_ID":{"0":"0021901235","1":"0021901235","2":"0021901244","3":"0021901244","4":"0021901244","5":"0021901244","6":"0021901244","7":"0021901278","8":"0021901278","9":"0021901278","10":"0021901285","11":"0021901285","12":"0021901285","13":"0021901285","14":"0021901285","15":"0021901285","16":"0021901285","17":"0021901285","18":"0021901303","19":"0021901303","20":"0021901303","21":"0021901308","22":"0021901308","23":"0021901308","24":"0021901308","25":"0021901308","26":"0021901308"},"GAME_EVENT_ID":{"0":189,"1":487,"2":160,"3":207,"4":212,"5":218,"6":609,"7":283,"8":475,"9":521,"10":112,"11":135,"12":157,"13":193,"14":458,"15":467,"16":525,"17":616,"18":689,"19":696,"20":728,"21":164,"22":194,"23":207,"24":264,"25":505,"26":525},"PLAYER_ID":{"0":1626170,"1":1626170,"2":1626170,"3":1626170,"4":1626170,"5":1626170,"6":1626170,"7":1626170,"8":1626170,"9":1626170,"10":1626170,"11":1626170,"12":1626170,"13":1626170,"14":1626170,"15":1626170,"16":1626170,"17":1626170,"18":1626170,"19":1626170,"20":1626170,"21":1626170,"22":1626170,"23":1626170,"24":1626170,"25":1626170,"26":1626170},"PLAYER_NAME":{"0":"Jerian Grant","1":"Jerian Grant","2":"Jerian Grant","3":"Jerian Grant","4":"Jerian Grant","5":"Jerian Grant","6":"Jerian Grant","7":"Jerian Grant","8":"Jerian Grant","9":"Jerian Grant","10":"Jerian Grant","11":"Jerian Grant","12":"Jerian Grant","13":"Jerian Grant","14":"Jerian Grant","15":"Jerian Grant","16":"Jerian Grant","17":"Jerian Grant","18":"Jerian Grant","19":"Jerian Grant","20":"Jerian Grant","21":"Jerian Grant","22":"Jerian Grant","23":"Jerian Grant","24":"Jerian Grant","25":"Jerian Grant","26":"Jerian Grant"},"TEAM_ID":{"0":1610612764,"1":1610612764,"2":1610612764,"3":1610612764,"4":1610612764,"5":1610612764,"6":1610612764,"7":1610612764,"8":1610612764,"9":1610612764,"10":1610612764,"11":1610612764,"12":1610612764,"13":1610612764,"14":1610612764,"15":1610612764,"16":1610612764,"17":1610612764,"18":1610612764,"19":1610612764,"20":1610612764,"21":1610612764,"22":1610612764,"23":1610612764,"24":1610612764,"25":1610612764,"26":1610612764},"TEAM_NAME":{"0":"Washington Wizards","1":"Washington Wizards","2":"Washington Wizards","3":"Washington Wizards","4":"Washington Wizards","5":"Washington Wizards","6":"Washington Wizards","7":"Washington Wizards","8":"Washington Wizards","9":"Washington Wizards","10":"Washington Wizards","11":"Washington Wizards","12":"Washington Wizards","13":"Washington Wizards","14":"Washington Wizards","15":"Washington Wizards","16":"Washington Wizards","17":"Washington Wizards","18":"Washington Wizards","19":"Washington Wizards","20":"Washington Wizards","21":"Washington Wizards","22":"Washington Wizards","23":"Washington Wizards","24":"Washington Wizards","25":"Washington Wizards","26":"Washington Wizards"},"PERIOD":{"0":2,"1":3,"2":1,"3":2,"4":2,"5":2,"6":4,"7":2,"8":3,"9":4,"10":1,"11":1,"12":1,"13":2,"14":3,"15":3,"16":4,"17":4,"18":4,"19":4,"20":4,"21":1,"22":2,"23":2,"24":2,"25":4,"26":4},"MINUTES_REMAINING":{"0":10,"1":1,"2":0,"3":9,"4":9,"5":8,"6":7,"7":3,"8":1,"9":10,"10":3,"11":2,"12":0,"13":8,"14":0,"15":0,"16":7,"17":0,"18":2,"19":2,"20":0,"21":1,"22":11,"23":10,"24":6,"25":11,"26":9},"SECONDS_REMAINING":{"0":25,"1":58,"2":58,"3":34,"4":6,"5":43,"6":16,"7":11,"8":0,"9":35,"10":55,"11":29,"12":31,"13":46,"14":51,"15":13,"16":19,"17":33,"18":30,"19":15,"20":14,"21":25,"22":34,"23":44,"24":8,"25":5,"26":11},"EVENT_TYPE":{"0":"Made Shot","1":"Made Shot","2":"Missed Shot","3":"Made Shot","4":"Made Shot","5":"Made Shot","6":"Made Shot","7":"Missed Shot","8":"Missed Shot","9":"Missed Shot","10":"Missed Shot","11":"Made Shot","12":"Missed Shot","13":"Made Shot","14":"Missed Shot","15":"Made Shot","16":"Missed Shot","17":"Missed Shot","18":"Missed Shot","19":"Missed Shot","20":"Missed Shot","21":"Missed Shot","22":"Missed Shot","23":"Made Shot","24":"Missed Shot","25":"Missed Shot","26":"Missed Shot"},"ACTION_TYPE":{"0":"Driving Floating Bank Jump Shot","1":"Running Jump Shot","2":"Jump Shot","3":"Driving Layup Shot","4":"Jump Shot","5":"Running Layup Shot","6":"Pullup Jump shot","7":"Driving Layup Shot","8":"Driving Layup Shot","9":"Driving Layup Shot","10":"Jump Shot","11":"Driving Finger Roll Layup Shot","12":"Jump Shot","13":"Driving Finger Roll Layup Shot","14":"Jump Shot","15":"Driving Floating Jump Shot","16":"Pullup Jump shot","17":"Jump Shot","18":"Jump Shot","19":"Pullup Jump shot","20":"Driving Layup Shot","21":"Running Layup Shot","22":"Driving Floating Jump Shot","23":"Driving Layup Shot","24":"Pullup Jump shot","25":"Driving Floating Jump Shot","26":"Fadeaway Jump Shot"},"SHOT_TYPE":{"0":"2PT Field Goal","1":"3PT Field Goal","2":"3PT Field Goal","3":"2PT Field Goal","4":"3PT Field Goal","5":"2PT Field Goal","6":"2PT Field Goal","7":"2PT Field Goal","8":"2PT Field Goal","9":"2PT Field Goal","10":"3PT Field Goal","11":"2PT Field Goal","12":"3PT Field Goal","13":"2PT Field Goal","14":"3PT Field Goal","15":"2PT Field Goal","16":"2PT Field Goal","17":"3PT Field Goal","18":"3PT Field Goal","19":"2PT Field Goal","20":"2PT Field Goal","21":"2PT Field Goal","22":"2PT Field Goal","23":"2PT Field Goal","24":"2PT Field Goal","25":"2PT Field Goal","26":"2PT Field Goal"},"SHOT_ZONE_BASIC":{"0":"In The Paint (Non-RA)","1":"Above the Break 3","2":"Above the Break 3","3":"Restricted Area","4":"Above the Break 3","5":"Restricted Area","6":"Mid-Range","7":"Restricted Area","8":"Restricted Area","9":"Restricted Area","10":"Above the Break 3","11":"Restricted Area","12":"Above the Break 3","13":"In The Paint (Non-RA)","14":"Right Corner 3","15":"In The Paint (Non-RA)","16":"In The Paint (Non-RA)","17":"Above the Break 3","18":"Above the Break 3","19":"Mid-Range","20":"Restricted Area","21":"Restricted Area","22":"In The Paint (Non-RA)","23":"Restricted Area","24":"Mid-Range","25":"In The Paint (Non-RA)","26":"In The Paint (Non-RA)"},"SHOT_ZONE_AREA":{"0":"Center(C)","1":"Left Side Center(LC)","2":"Center(C)","3":"Center(C)","4":"Left Side Center(LC)","5":"Center(C)","6":"Left Side Center(LC)","7":"Center(C)","8":"Center(C)","9":"Center(C)","10":"Right Side Center(RC)","11":"Center(C)","12":"Left Side Center(LC)","13":"Center(C)","14":"Right Side(R)","15":"Center(C)","16":"Center(C)","17":"Center(C)","18":"Left Side Center(LC)","19":"Right Side Center(RC)","20":"Center(C)","21":"Center(C)","22":"Center(C)","23":"Center(C)","24":"Left Side(L)","25":"Center(C)","26":"Center(C)"},"SHOT_ZONE_RANGE":{"0":"Less Than 8 ft.","1":"24+ ft.","2":"24+ ft.","3":"Less Than 8 ft.","4":"24+ ft.","5":"Less Than 8 ft.","6":"16-24 ft.","7":"Less Than 8 ft.","8":"Less Than 8 ft.","9":"Less Than 8 ft.","10":"24+ ft.","11":"Less Than 8 ft.","12":"24+ ft.","13":"Less Than 8 ft.","14":"24+ ft.","15":"8-16 ft.","16":"Less Than 8 ft.","17":"24+ ft.","18":"24+ ft.","19":"16-24 ft.","20":"Less Than 8 ft.","21":"Less Than 8 ft.","22":"8-16 ft.","23":"Less Than 8 ft.","24":"8-16 ft.","25":"8-16 ft.","26":"8-16 ft."},"SHOT_DISTANCE":{"0":5,"1":26,"2":27,"3":1,"4":25,"5":1,"6":20,"7":0,"8":1,"9":3,"10":25,"11":0,"12":25,"13":4,"14":22,"15":11,"16":7,"17":27,"18":26,"19":21,"20":3,"21":0,"22":8,"23":2,"24":14,"25":13,"26":8},"LOC_X":{"0":47,"1":-198,"2":34,"3":11,"4":-114,"5":11,"6":-107,"7":-1,"8":-11,"9":-19,"10":115,"11":3,"12":-107,"13":22,"14":223,"15":-12,"16":67,"17":-6,"18":-145,"19":102,"20":-9,"21":-8,"22":7,"23":20,"24":-90,"25":11,"26":25},"LOC_Y":{"0":32,"1":169,"2":272,"3":11,"4":226,"5":11,"6":173,"7":2,"8":13,"9":31,"10":231,"11":4,"12":235,"13":35,"14":17,"15":111,"16":21,"17":277,"18":220,"19":184,"20":32,"21":0,"22":83,"23":1,"24":113,"25":133,"26":85},"SHOT_ATTEMPTED_FLAG":{"0":1,"1":1,"2":1,"3":1,"4":1,"5":1,"6":1,"7":1,"8":1,"9":1,"10":1,"11":1,"12":1,"13":1,"14":1,"15":1,"16":1,"17":1,"18":1,"19":1,"20":1,"21":1,"22":1,"23":1,"24":1,"25":1,"26":1},"SHOT_MADE_FLAG":{"0":1,"1":1,"2":0,"3":1,"4":1,"5":1,"6":1,"7":0,"8":0,"9":0,"10":0,"11":1,"12":0,"13":1,"14":0,"15":1,"16":0,"17":0,"18":0,"19":0,"20":0,"21":0,"22":0,"23":1,"24":0,"25":0,"26":0},"GAME_DATE":{"0":"20200731","1":"20200731","2":"20200802","3":"20200802","4":"20200802","5":"20200802","6":"20200802","7":"20200807","8":"20200807","9":"20200807","10":"20200809","11":"20200809","12":"20200809","13":"20200809","14":"20200809","15":"20200809","16":"20200809","17":"20200809","18":"20200811","19":"20200811","20":"20200811","21":"20200813","22":"20200813","23":"20200813","24":"20200813","25":"20200813","26":"20200813"},"HTM":{"0":"WAS","1":"WAS","2":"BKN","3":"BKN","4":"BKN","5":"BKN","6":"BKN","7":"NOP","8":"NOP","9":"NOP","10":"OKC","11":"OKC","12":"OKC","13":"OKC","14":"OKC","15":"OKC","16":"OKC","17":"OKC","18":"WAS","19":"WAS","20":"WAS","21":"BOS","22":"BOS","23":"BOS","24":"BOS","25":"BOS","26":"BOS"},"VTM":{"0":"PHX","1":"PHX","2":"WAS","3":"WAS","4":"WAS","5":"WAS","6":"WAS","7":"WAS","8":"WAS","9":"WAS","10":"WAS","11":"WAS","12":"WAS","13":"WAS","14":"WAS","15":"WAS","16":"WAS","17":"WAS","18":"MIL","19":"MIL","20":"MIL","21":"WAS","22":"WAS","23":"WAS","24":"WAS","25":"WAS","26":"WAS"}}